[
 {
  "appIcon": "https://lh3.googleusercontent.com/7p0QQlN7vmjaJhz2r-seNe253jJxmH_dpzU_OWMy9EPyVqot9yyDvecF-9zF8B2k9MU",
  "appName": "Just ಕನ್ನಡ Keyboard",
  "appDescription": "ಸಿರಿಗನ್ನಡಂ ಗೆಲ್ಗೆ, ಸಿರಿಗನ್ನಡಂ ಬಾಳ್ಗೆ, ಸಿರಿಗನ್ನಡಂ ಮೊಬೈಲ್ಗೆ!",
  "url": "https://play.google.com/store/apps/details?id=com.sriandroid.justkannada",
  "type": "DISABLEapp_text_banner"
 },
 {
  "appIcon": "https://lh3.googleusercontent.com/7p0QQlN7vmjaJhz2r-seNe253jJxmH_dpzU_OWMy9EPyVqot9yyDvecF-9zF8B2k9MU",
  "appName": "Just ಕನ್ನಡ Keyboard",
  "appDescription": "ಜಾಹೀರಾತು ಮುಕ್ತ ಅನುಭವಕ್ಕಾಗಿ ಗೂಗಲ್ ಪ್ಲೇ ಸ್ಟೋರ್ ಚಂದಾದರರಾಗಿ",
  "url": "https://play.google.com/store/apps/details?id=com.sriandroid.justkannada",
  "type": "app_text_banner"
 },
 {
  "appIcon": "https://lh3.googleusercontent.com/7p0QQlN7vmjaJhz2r-seNe253jJxmH_dpzU_OWMy9EPyVqot9yyDvecF-9zF8B2k9MU",
  "appName": "Just ಕನ್ನಡ Keyboard",
  "appDescription": "ಜಸ್ಟ್ ಕನ್ನಡ ಕೀಲಿಮಣೆ ಈಗ ಆಪಲ್ ಐಒಎಸ್ ನಲ್ಲಿಯೂ ಲಭ್ಯ",
  "url": "none",
  "type": "DISABLEmsg_text_banner"
 },
 {
  "appIcon": "https://raw.githubusercontent.com/sridharrn/public/master/kapata.png",
  "appName": "Just ಕನ್ನಡ Keyboard",
  "appDescription": "ಜಸ್ಟ್ ಕನ್ನಡ ಕೀಲಿಮಣೆ ಈಗ ಆಪಲ್ ಐಒಎಸ್ ನಲ್ಲಿಯೂ ಲಭ್ಯ",
  "url": "https://in.bookmyshow.com/bengaluru/movies/shivaji-surathkal/ET00124967",
  "type": "msg_image_banner"
 }
]